ctower/__init__.py
ctower/cli.py
ctower/guardrail_identifiers.py
ctower/main.py
ctower/utilities.py
ctower-0.1.0.dist-info/entry_points.txt
ctower-0.1.0.dist-info/LICENSE
ctower-0.1.0.dist-info/WHEEL
ctower-0.1.0.dist-info/METADATA
ctower-0.1.0.dist-info/RECORD
